coinwrap
