Metadata-Version: 1.1
Name: coinwrap
Version: 0.1.5
Summary: Python wrapper created for https://coinmarketcap.com API
Home-page: https://github.com/bitforce/coinwrap
Author: Brandon Johnson
Author-email: brandon.johnson.official@gmail.com
License:            DO WHAT THE FUCK YOU WANT TO PUBLIC LICENSE
